LICENSE
MANIFEST.in
README.rst
helga_mail.py
setup.py
helga_mail.egg-info/PKG-INFO
helga_mail.egg-info/SOURCES.txt
helga_mail.egg-info/dependency_links.txt
helga_mail.egg-info/entry_points.txt
helga_mail.egg-info/top_level.txt
helga_mail.egg-info/zip-safe