Metadata-Version: 1.1
Name: helga-mail
Version: 1.0.2
Summary: mail for irc
Home-page: UNKNOWN
Author: Justin Caratzas
Author-email: bigjust@lambdaphil.es
License: LICENSE
Keywords: irc bot mail
Platform: UNKNOWN
Classifier: Development Status :: 1 - Planning
Classifier: License :: OSI Approved :: GNU General Public License v3 (GPLv3)
Classifier: Operating System :: OS Independent
Classifier: Programming Language :: Python
Classifier: Topic :: Software Development :: Libraries :: Python Modules
